{"stats":{"minecraft:mined":{"minecraft:sand":1},"minecraft:custom":{"minecraft:jump":70,"minecraft:time_since_rest":3982,"minecraft:leave_game":5,"minecraft:play_time":3982,"minecraft:sprint_one_cm":15442,"minecraft:time_since_death":3982,"minecraft:walk_on_water_one_cm":884,"minecraft:walk_one_cm":2840,"minecraft:total_world_time":3982,"minecraft:walk_under_water_one_cm":196,"minecraft:fall_one_cm":2299,"minecraft:fly_one_cm":15155},"minecraft:used":{"minecraft:sand":1},"minecraft:picked_up":{"minecraft:sand":1}},"DataVersion":3578}